surveymars_mcp/__init__.py
surveymars_mcp/scheme.py
surveymars_mcp/server.py
surveymars_mcp/fetcher/__init__.py
surveymars_mcp/fetcher/config.py
surveymars_mcp-0.1.1.dist-info/METADATA
surveymars_mcp-0.1.1.dist-info/WHEEL
surveymars_mcp-0.1.1.dist-info/entry_points.txt
surveymars_mcp-0.1.1.dist-info/RECORD
