Metadata-Version: 2.4
Name: surveymars-mcp
Version: 0.1.1
Summary: SurveyMars MCP server
Keywords: Survey,SurveyMars,mcp
Requires-Python: >=3.11
Requires-Dist: mcp>=1.6.0
